pixelcount/__init__.py
pixelcount/algorithm.py
pixelcount/frontend.ipynb
pixelcount/frontend.py
pixelcount_samples-0.0.2.0.dist-info/LICENSE
pixelcount_samples-0.0.2.0.dist-info/METADATA
pixelcount_samples-0.0.2.0.dist-info/WHEEL
pixelcount_samples-0.0.2.0.dist-info/top_level.txt
pixelcount_samples-0.0.2.0.dist-info/RECORD
